example/__init__.py
example/model_pruning_example.py
example/test.py
example/cifar_10_resnet/__init__.py
example/cifar_10_resnet/resnet.py
ridurre/__init__.py
ridurre/base_filter_pruning.py
ridurre/kmeans_pruning.py
ridurre/random_pruning.py
ridurre/ultimate_prune.py
ridurre/model_complexity/__init__.py
ridurre/model_complexity/graph_complexity.py
ridurre-0.0.2.dist-info/LICENSE
ridurre-0.0.2.dist-info/METADATA
ridurre-0.0.2.dist-info/WHEEL
ridurre-0.0.2.dist-info/top_level.txt
ridurre-0.0.2.dist-info/RECORD
